{
	"page": {
		"currPage": 1,
		"list": [{
			"appQcodeLink": "http://employee.feser.com.cn/#/home?taskId=task20180712000011",
			"busiCusts": [{
				"busiCustName": "北京肯德基有限公司",
				"busiCustNo": "430676"
			}],
			"creator": "hr3",
			"creatorName": "周成敏",
			"delFlag": null,
			"guides": "1",
			"guidesList": [{
				"content": "<p>测试            json</p>",
				"taskGuideId": "15",
				"guideId": "1",
			  "guideName":"劳动合同"
			}],
			"importNum": 0,
			"otherGuideContent": "",
			"otherGuideName": "",
			"pcEntryLink": "http://employee.feser.com.cn/#/home?taskId=task20180712000011",
			"procedures": "1",
			"registerNum": 0,
			"taskId": "task20180712000011",
			"taskName": "测试4",
			"taskStatus": null,
			"taskType": null,
			"wxQcodeLink": "http://employee.feser.com.cn/#/home?taskId=task20180712000011"
		}, {
			"appQcodeLink": "http://employee.feser.com.cn/#/home?taskId=task20180716000012",
			"busiCusts": [{
				"busiCustName": "北京肯德基有限公司",
				"busiCustNo": "430676"
			}],
			"creator": "hr3",
			"creatorName": "周成敏",
			"delFlag": null,
			"guides": "1",
			"importNum": 0,
			"otherGuideContent": "",
			"otherGuideName": "",
			"pcEntryLink": "http://employee.feser.com.cn/#/home?taskId=task20180716000012",
			"procedures": "1",
			"registerNum": 0,
			"taskId": "task20180716000012",
			"taskName": "测试4- 张利",
			"taskStatus": null,
			"taskType": null,
			"wxQcodeLink": "http://employee.feser.com.cn/#/home?taskId=task20180716000012"
		}, {
			"appQcodeLink": "http://employee.feser.com.cn/#/home?taskId=task20180716000014",
			"busiCusts": [{
				"busiCustName": "北京肯德基有限公司",
				"busiCustNo": "430676"
			}],
			"creator": "hr3",
			"creatorName": "周成敏",
			"delFlag": null,
			"guides": "1",
			"importNum": 0,
			"otherGuideContent": "",
			"otherGuideName": "",
			"pcEntryLink": "http://employee.feser.com.cn/#/home?taskId=task20180716000014",
			"procedures": "1",
			"registerNum": 0,
			"taskId": "task20180716000014",
			"taskName": "答复",
			"taskStatus": null,
			"taskType": null,
			"wxQcodeLink": "http://employee.feser.com.cn/#/home?taskId=task20180716000014"
		}, {
			"appQcodeLink": "http://employee.feser.com.cn/#/home?taskId=task20180716000018",
			"busiCusts": [{
				"busiCustName": "北京肯德基有限公司",
				"busiCustNo": "430676"
			}],
			"creator": "hr3",
			"creatorName": "周成敏",
			"delFlag": null,
			"guides": "1",
			"importNum": 0,
			"otherGuideContent": "",
			"otherGuideName": "",
			"pcEntryLink": "http://employee.feser.com.cn/#/home?taskId=task20180716000018",
			"procedures": "1",
			"registerNum": 0,
			"taskId": "task20180716000018",
			"taskName": "测试5-张利",
			"taskStatus": null,
			"taskType": null,
			"wxQcodeLink": "http://employee.feser.com.cn/#/home?taskId=task20180716000018"
		}, {
			"appQcodeLink": "http://employee.feser.com.cn/#/home?taskId=task20180716000019",
			"busiCusts": [{
				"busiCustName": "北京必胜客比萨饼有限公司",
				"busiCustNo": "430678"
			}],
			"creator": "hr3",
			"creatorName": "周成敏",
			"delFlag": null,
			"guides": "1,2,3",
			"importNum": 0,
			"otherGuideContent": "",
			"otherGuideName": "",
			"pcEntryLink": "http://employee.feser.com.cn/#/home?taskId=task20180716000019",
			"procedures": "1",
			"registerNum": 0,
			"taskId": "task20180716000019",
			"taskName": "测试6-张利",
			"taskStatus": null,
			"taskType": null,
			"wxQcodeLink": "http://employee.feser.com.cn/#/home?taskId=task20180716000019"
		}, {
			"appQcodeLink": "http://employee.feser.com.cn/#/home?taskId=task20180716000020",
			"busiCusts": [{
				"busiCustName": "北京肯德基有限公司",
				"busiCustNo": "430676"
			}],
			"creator": "hr3",
			"creatorName": "周成敏",
			"delFlag": null,
			"guides": "1",
			"importNum": 0,
			"otherGuideContent": "",
			"otherGuideName": "",
			"pcEntryLink": "http://employee.feser.com.cn/#/home?taskId=task20180716000020",
			"procedures": "1",
			"registerNum": 0,
			"taskId": "task20180716000020",
			"taskName": "测试7",
			"taskStatus": null,
			"taskType": null,
			"wxQcodeLink": "http://employee.feser.com.cn/#/home?taskId=task20180716000020"
		}, {
			"appQcodeLink": "http://employee.feser.com.cn/#/home?taskId=task20180716000021",
			"busiCusts": [{
				"busiCustName": "北京肯德基有限公司",
				"busiCustNo": "430676"
			}, {
				"busiCustName": "北京必胜客比萨饼有限公司",
				"busiCustNo": "430678"
			}],
			"creator": "hr3",
			"creatorName": "周成敏",
			"delFlag": null,
			"guides": "1,2,3",
			"importNum": 0,
			"otherGuideContent": "",
			"otherGuideName": "",
			"pcEntryLink": "http://employee.feser.com.cn/#/home?taskId=task20180716000021",
			"procedures": "1,2,3",
			"registerNum": 0,
			"taskId": "task20180716000021",
			"taskName": "测试8-张利",
			"taskStatus": null,
			"taskType": null,
			"wxQcodeLink": "http://employee.feser.com.cn/#/home?taskId=task20180716000021"
		}, {
			"appQcodeLink": "http://employee.feser.com.cn/#/home?taskId=task20180716000022",
			"busiCusts": [{
				"busiCustName": "北京肯德基有限公司",
				"busiCustNo": "430676"
			}],
			"creator": "hr3",
			"creatorName": "周成敏",
			"delFlag": null,
			"guides": "1",
			"importNum": 0,
			"otherGuideContent": "",
			"otherGuideName": "",
			"pcEntryLink": "http://employee.feser.com.cn/#/home?taskId=task20180716000022",
			"procedures": "1",
			"registerNum": 0,
			"taskId": "task20180716000022",
			"taskName": "测试8",
			"taskStatus": null,
			"taskType": null,
			"wxQcodeLink": "http://employee.feser.com.cn/#/home?taskId=task20180716000022"
		}, {
			"appQcodeLink": "http://employee.feser.com.cn/#/home?taskId=task20180716000024",
			"busiCusts": [{
				"busiCustName": "北京肯德基有限公司",
				"busiCustNo": "430676"
			}],
			"creator": "hr3",
			"creatorName": "周成敏",
			"delFlag": null,
			"guides": "1",
			"importNum": 0,
			"otherGuideContent": "",
			"otherGuideName": "",
			"pcEntryLink": "http://employee.feser.com.cn/#/home?taskId=task20180716000024",
			"procedures": "1",
			"registerNum": 0,
			"taskId": "task20180716000024",
			"taskName": "测试10",
			"taskStatus": null,
			"taskType": null,
			"wxQcodeLink": "http://employee.feser.com.cn/#/home?taskId=task20180716000024"
		}],
		"pageSize": 10,
		"totalCount": 9,
		"totalPage": 1
	},
	"code": 0
}